opensecrets/__init__.py
opensecrets/crpapi.py
opensecrets/exceptions.py
py_opensecrets-0.3.1.dist-info/METADATA
py_opensecrets-0.3.1.dist-info/RECORD
py_opensecrets-0.3.1.dist-info/WHEEL
py_opensecrets-0.3.1.dist-info/top_level.txt
