Metadata-Version: 2.1
Name: py-opensecrets
Version: 0.3.1
Summary: Libraries for interacting with the Opensecrets API
Home-page: http://github.com/ndanielsen/py-opensecrets/
Author: Nathan Danielsen <nathan.danielsen@gmail.com>
Author-email: nathan.danielsen@gmail.com
License: BSD
Platform: any
Classifier: Development Status :: 3 - Alpha
Classifier: Intended Audience :: Developers
Classifier: License :: OSI Approved :: BSD License
Classifier: Natural Language :: English
Classifier: Operating System :: OS Independent
Classifier: Programming Language :: Python
Classifier: Topic :: Software Development :: Libraries :: Python Modules
Classifier: Programming Language :: Python
Classifier: Programming Language :: Python :: 2.7
Classifier: Programming Language :: Python :: 3.4
Classifier: Programming Language :: Python :: 3.5
Classifier: Programming Language :: Python :: 3.6
Requires-Dist: requests (>=2.7.0)
